.travis.yml
LICENSE
MANIFEST.in
README.rst
setup.py
Mopidy_radio_de.egg-info/PKG-INFO
Mopidy_radio_de.egg-info/SOURCES.txt
Mopidy_radio_de.egg-info/dependency_links.txt
Mopidy_radio_de.egg-info/entry_points.txt
Mopidy_radio_de.egg-info/not-zip-safe
Mopidy_radio_de.egg-info/requires.txt
Mopidy_radio_de.egg-info/top_level.txt
mopidy_radio_de/__init__.py
mopidy_radio_de/actor.py
mopidy_radio_de/api.py
mopidy_radio_de/ext.conf
mopidy_radio_de/library.py
mopidy_radio_de/playlists.py
tests/__init__.py
tests/test_extension.py