Metadata-Version: 1.0
Name: Mopidy-radio-de
Version: 0.2.0
Summary: radio.de extension for Mopidy
Home-page: http://github.com/hechtus/mopidy-radio-de/
Author: Ronald Hecht
Author-email: ronald.hecht@gmx.de
License: Apache License, Version 2.0
Platform: UNKNOWN
Classifier: Environment :: No Input/Output (Daemon)
Classifier: Intended Audience :: End Users/Desktop
Classifier: License :: OSI Approved :: MIT License
Classifier: Operating System :: OS Independent
Classifier: Programming Language :: Python :: 2
Classifier: Topic :: Multimedia :: Sound/Audio :: Players
